regfmt/CommandLineParser.py
regfmt/Constants.py
regfmt/DRCChecker.py
regfmt/Endian.py
regfmt/Field.py
regfmt/InputLoadAndValidate.py
regfmt/Register.py
regfmt/RegisterFormat.py
regfmt/RegisterTemplate.py
regfmt/TopLevel.py
regfmt/__init__.py
regfmt/centeralignlayout.py
regfmt/cssparser.py
regfmt/cssstyles.py
regfmt/stairleftlayout.py
regfmt/svggeometry.py
regfmt/svgwriter.py
regfmt-0.9.1.dist-info/LICENSE
regfmt-0.9.1.dist-info/METADATA
regfmt-0.9.1.dist-info/WHEEL
regfmt-0.9.1.dist-info/entry_points.txt
regfmt-0.9.1.dist-info/top_level.txt
regfmt-0.9.1.dist-info/RECORD
