Metadata-Version: 2.1
Name: regfmt
Version: 0.9.1
Summary: A command line utility to generate SVG diagrams for control register-style data formats.
Author-email: Charles Choi <kickingvegas@gmail.com>
Project-URL: Homepage, https://github.com/kickingvegas/regfmt
Project-URL: Issue Tracker, https://github.com/kickingvegas/regfmt/issues
Classifier: Programming Language :: Python :: 3.9
Classifier: Programming Language :: Python :: 3.10
Classifier: License :: OSI Approved :: Apache Software License
Classifier: Operating System :: OS Independent
Requires-Python: >=3.9
License-File: LICENSE
Requires-Dist: attrs (>=22.1.0)
Requires-Dist: jsonschema (>=4.16.0)
Requires-Dist: Pillow (>=9.2.0)
Requires-Dist: pyrsistent (>=0.18.1)
Requires-Dist: PyYAML (>=6.0)
Requires-Dist: tinycss2 (>=1.1.1)
Requires-Dist: webencodings (>=0.5.1)
